command_timeout/__init__.py
command_timeout/__main__.py
command_timeout-1.2.dist-info/DESCRIPTION.rst
command_timeout-1.2.dist-info/METADATA
command_timeout-1.2.dist-info/RECORD
command_timeout-1.2.dist-info/WHEEL
command_timeout-1.2.dist-info/entry_points.txt
command_timeout-1.2.dist-info/metadata.json
command_timeout-1.2.dist-info/top_level.txt
