Metadata-Version: 2.0
Name: command-timeout
Version: 1.2
Summary: Timeout Commands
Home-page: UNKNOWN
Author: xoviat
Author-email: xoviat@noreply.users.github.com
License: UNKNOWN
Platform: UNKNOWN
Requires-Dist: psutil
Requires-Dist: typing; python_version < "3.5"
